odoo8_addon_website_sale_vat_required-8.0.1.0.0.99.dev4-py2.7-nspkg.pth
odoo8_addon_website_sale_vat_required-8.0.1.0.0.99.dev4.dist-info/METADATA
odoo8_addon_website_sale_vat_required-8.0.1.0.0.99.dev4.dist-info/RECORD
odoo8_addon_website_sale_vat_required-8.0.1.0.0.99.dev4.dist-info/WHEEL
odoo8_addon_website_sale_vat_required-8.0.1.0.0.99.dev4.dist-info/namespace_packages.txt
odoo8_addon_website_sale_vat_required-8.0.1.0.0.99.dev4.dist-info/top_level.txt
odoo_addons/website_sale_vat_required/README.rst
odoo_addons/website_sale_vat_required/__init__.py
odoo_addons/website_sale_vat_required/__openerp__.py
odoo_addons/website_sale_vat_required/website_order_view.xml
odoo_addons/website_sale_vat_required/controllers/__init__.py
odoo_addons/website_sale_vat_required/controllers/main.py
odoo_addons/website_sale_vat_required/i18n/website_sale_vat_required.pot
odoo_addons/website_sale_vat_required/static/description/icon.png
